AUTHORS
LICENSE
MANIFEST.in
README.md
setup.py
batinfo/__init__.py
batinfo/battery.py
batinfo.egg-info/PKG-INFO
batinfo.egg-info/SOURCES.txt
batinfo.egg-info/dependency_links.txt
batinfo.egg-info/top_level.txt